pyrus_decision_tree-0.1.1.dist-info/METADATA
pyrus_decision_tree-0.1.1.dist-info/WHEEL
pyrus_decision_tree.cpython-36m-x86_64-linux-gnu.so
pyrus_decision_tree-0.1.1.dist-info/RECORD
