Metadata-Version: 2.1
Name: pyrus-decision-tree
Version: 0.1.1
Keywords: machine learning decision tree data science
Author: Miles Granger <miles59923@gmail.com>
Author-Email: Miles Granger <miles59923@gmail.com>
